plastro/__init__.py
plastro/lineage_simulation.py
plastro/overlap.py
plastro/overlap_archive.py
plastro/phenotype_simulation.py
plastro/phylo.py
plastro/plasticity.py
plastro-0.1.3.dist-info/licenses/LICENSE
plastro-0.1.3.dist-info/METADATA
plastro-0.1.3.dist-info/WHEEL
plastro-0.1.3.dist-info/top_level.txt
plastro-0.1.3.dist-info/RECORD
