Metadata-Version: 2.4
Name: plastro
Version: 0.1.3
Summary: A Python package for simulating cellular plasticity in single-cell data
Home-page: https://github.com/username/plastro
Author: Sitara Persad
Author-email: Sitara Persad <sitara.persad@example.com>
Maintainer-email: Sitara Persad <sitara.persad@example.com>
License-Expression: MIT
Project-URL: Homepage, https://github.com/dpeerlab/PLASTRO
Project-URL: Documentation, https://plastro.readthedocs.io/
Project-URL: Repository, https://github.com/dpeerlab/PLASTRO.git
Project-URL: Bug Tracker, https://github.com/dpeerlab/PLASTRO/issues
Project-URL: Changelog, https://github.com/dpeerlab/PLASTRO/blob/main/CHANGELOG.md
Keywords: single-cell,plasticity,lineage-tracing,phylogeny,bioinformatics,computational-biology,cellular-plasticity,CRISPR
Classifier: Development Status :: 3 - Alpha
Classifier: Intended Audience :: Science/Research
Classifier: Topic :: Scientific/Engineering :: Bio-Informatics
Classifier: Programming Language :: Python :: 3
Classifier: Programming Language :: Python :: 3.8
Classifier: Programming Language :: Python :: 3.9
Classifier: Programming Language :: Python :: 3.10
Classifier: Programming Language :: Python :: 3.11
Classifier: Operating System :: OS Independent
Requires-Python: >=3.8
License-File: LICENSE
Requires-Dist: pybind11>=2.6.0
Requires-Dist: graph-walker>=1.0.6
Requires-Dist: numpy>=1.20.0
Requires-Dist: pandas>=1.3.0
Requires-Dist: scipy>=1.7.0
Requires-Dist: matplotlib>=3.4.0
Requires-Dist: seaborn>=0.11.0
Requires-Dist: scanpy>=1.8.0
Requires-Dist: anndata>=0.8.0
Requires-Dist: networkx>=2.6.0
Requires-Dist: ete3>=3.1.2
Requires-Dist: scikit-learn>=1.0.0
Requires-Dist: tqdm>=4.60.0
Requires-Dist: icecream>=2.1.0
Requires-Dist: scikit-bio>=0.5.7
Provides-Extra: dev
Requires-Dist: pytest>=6.0; extra == "dev"
Requires-Dist: pytest-cov>=2.0; extra == "dev"
Requires-Dist: black>=21.0; extra == "dev"
Requires-Dist: flake8>=3.8; extra == "dev"
Requires-Dist: mypy>=0.8; extra == "dev"
Requires-Dist: pre-commit>=2.0; extra == "dev"
Provides-Extra: docs
Requires-Dist: sphinx>=4.0; extra == "docs"
Requires-Dist: sphinx-rtd-theme>=1.0; extra == "docs"
Requires-Dist: nbsphinx>=0.8; extra == "docs"
Requires-Dist: pandoc>=1.0; extra == "docs"
Provides-Extra: notebooks
Requires-Dist: jupyter>=1.0; extra == "notebooks"
Requires-Dist: ipykernel>=6.0; extra == "notebooks"
Requires-Dist: matplotlib>=3.0; extra == "notebooks"
Requires-Dist: seaborn>=0.11; extra == "notebooks"
Provides-Extra: lineage
Requires-Dist: cassiopeia-lineage>=2.0.0; extra == "lineage"
Requires-Dist: igraph>=0.10.0; extra == "lineage"
Provides-Extra: clustering
Requires-Dist: igraph>=0.10.0; extra == "clustering"
Provides-Extra: all
Requires-Dist: plastro[clustering,dev,docs,lineage,notebooks]; extra == "all"
Dynamic: author
Dynamic: home-page
Dynamic: license-file
Dynamic: requires-python
